{
  "$schema": "https://developer.microsoft.com/json-schemas/fabric/item/report/definition/visualContainer/2.4.0/schema.json",
  "name": "b42bc14105b7e88b10f2",
  "position": {
    "x": 39.854625550660785,
    "y": 74.881057268722472,
    "z": 2000,
    "height": 24.810572687224671,
    "width": 85,
    "tabOrder": 23000
  },
  "visual": {
    "visualType": "card",
    "query": {
      "queryState": {
        "Values": {
          "projections": [
            {
              "field": {
                "Measure": {
                  "Expression": {
                    "SourceRef": {
                      "Entity": "Medidas"
                    }
                  },
                  "Property": "% Qtd Abertos YoY"
                }
              },
              "queryRef": "Medidas.% Qtd Abertos YoY"
            }
          ]
        }
      },
      "sortDefinition": {
        "sort": [
          {
            "field": {
              "Measure": {
                "Expression": {
                  "SourceRef": {
                    "Entity": "Medidas"
                  }
                },
                "Property": "% Qtd Abertos YoY"
              }
            },
            "direction": "Descending"
          }
        ],
        "isDefaultSort": true
      }
    },
    "objects": {
      "categoryLabels": [
        {
          "properties": {
            "show": {
              "expr": {
                "Literal": {
                  "Value": "false"
                }
              }
            }
          }
        }
      ],
      "labels": [
        {
          "properties": {
            "fontSize": {
              "expr": {
                "Literal": {
                  "Value": "10D"
                }
              }
            },
            "bold": {
              "expr": {
                "Literal": {
                  "Value": "true"
                }
              }
            },
            "color": {
              "solid": {
                "color": {
                  "expr": {
                    "Conditional": {
                      "Cases": [
                        {
                          "Condition": {
                            "Comparison": {
                              "ComparisonKind": 2,
                              "Left": {
                                "Measure": {
                                  "Expression": {
                                    "SourceRef": {
                                      "Entity": "Medidas"
                                    }
                                  },
                                  "Property": "% Qtd Abertos YoY"
                                }
                              },
                              "Right": {
                                "Literal": {
                                  "Value": "0.05D"
                                }
                              }
                            }
                          },
                          "Value": {
                            "Literal": {
                              "Value": "'#DC5B57'"
                            }
                          }
                        },
                        {
                          "Condition": {
                            "And": {
                              "Left": {
                                "Comparison": {
                                  "ComparisonKind": 2,
                                  "Left": {
                                    "Measure": {
                                      "Expression": {
                                        "SourceRef": {
                                          "Entity": "Medidas"
                                        }
                                      },
                                      "Property": "% Qtd Abertos YoY"
                                    }
                                  },
                                  "Right": {
                                    "Literal": {
                                      "Value": "-0.05D"
                                    }
                                  }
                                }
                              },
                              "Right": {
                                "Comparison": {
                                  "ComparisonKind": 3,
                                  "Left": {
                                    "Measure": {
                                      "Expression": {
                                        "SourceRef": {
                                          "Entity": "Medidas"
                                        }
                                      },
                                      "Property": "% Qtd Abertos YoY"
                                    }
                                  },
                                  "Right": {
                                    "Literal": {
                                      "Value": "0.05D"
                                    }
                                  }
                                }
                              }
                            }
                          },
                          "Value": {
                            "Literal": {
                              "Value": "'#F3C911'"
                            }
                          }
                        },
                        {
                          "Condition": {
                            "Comparison": {
                              "ComparisonKind": 3,
                              "Left": {
                                "Measure": {
                                  "Expression": {
                                    "SourceRef": {
                                      "Entity": "Medidas"
                                    }
                                  },
                                  "Property": "% Qtd Abertos YoY"
                                }
                              },
                              "Right": {
                                "Literal": {
                                  "Value": "-0.05D"
                                }
                              }
                            }
                          },
                          "Value": {
                            "Literal": {
                              "Value": "'#33AE81'"
                            }
                          }
                        }
                      ]
                    }
                  }
                }
              }
            }
          }
        }
      ]
    },
    "visualContainerObjects": {
      "background": [
        {
          "properties": {
            "show": {
              "expr": {
                "Literal": {
                  "Value": "false"
                }
              }
            }
          }
        }
      ],
      "title": [
        {
          "properties": {
            "text": {
              "expr": {
                "Literal": {
                  "Value": "'% Total Abertos'"
                }
              }
            }
          }
        }
      ],
      "visualHeader": [
        {
          "properties": {
            "show": {
              "expr": {
                "Literal": {
                  "Value": "false"
                }
              }
            }
          }
        }
      ]
    },
    "drillFilterOtherVisuals": true
  },
  "parentGroupName": "e0a02113731ef3a4e03f"
}